ircodec/__init__.py
ircodec/command.py
ircodec/signal.py
ircodec/utils.py
ircodec-0.3.0.dist-info/LICENSE
ircodec-0.3.0.dist-info/METADATA
ircodec-0.3.0.dist-info/WHEEL
ircodec-0.3.0.dist-info/top_level.txt
ircodec-0.3.0.dist-info/RECORD
