Metadata-Version: 2.1
Name: ircodec
Version: 0.3.0
Summary: Send and receive IR commands using pigpio
Home-page: https://github.com/kentwait/ircodec
Author: Kent Kawashima
Author-email: kentkawashima@gmail.com
License: UNKNOWN
Keywords: pigpio,ir,raspberry,pi
Platform: UNKNOWN
Classifier: Programming Language :: Python :: 3
Classifier: Programming Language :: Python :: 3.4
Classifier: Programming Language :: Python :: 3.5
Classifier: Programming Language :: Python :: 3.6
Classifier: License :: OSI Approved :: MIT License
Classifier: Operating System :: OS Independent
